tests/__init__.py
tests/test_cli.py
tests/test_tproj.py
tproj/__init__.py
tproj/apply.py
tproj/cli.py
tproj/create.py
tproj/ls.py
tproj/utils/__init__.py
tproj_zombie110year-1.0.3.dist-info/LICENSE
tproj_zombie110year-1.0.3.dist-info/METADATA
tproj_zombie110year-1.0.3.dist-info/WHEEL
tproj_zombie110year-1.0.3.dist-info/entry_points.txt
tproj_zombie110year-1.0.3.dist-info/top_level.txt
tproj_zombie110year-1.0.3.dist-info/RECORD
