Metadata-Version: 2.1
Name: tproj-zombie110year
Version: 1.0.3
Summary: tproj 用于管理用户创建的项目模板，一个项目所需的起始文件、目录被包含在一个 zip 格式的压缩包中。
Home-page: https://github.com/zombie110year/tproj-py/
Author: zombie110year
Author-email: zombie110year@outlook.com
License: UNKNOWN
Platform: UNKNOWN
Requires-Python: >=3.7,<4.0
Requires-Dist: pyyaml (<6.0,>=5.3)
